nlp_utils/__init__.py
nlp_utils/unidata.py
nlp_utils/vocabulary.py
nlp_utils/chars/__init__.py
nlp_utils/chars/char_set.py
nlp_utils/chars/fullwidth_halfwidth.py
nlp_utils/chars/generate_gb18030.py
nlp_utils/chars/punc.py
nlp_utils/chars/symbols.py
nlp_utils/chars/variety_to_normal.py
nlp_utils/dataset/__init__.py
nlp_utils/dataset/download.py
nlp_utils/embedding/__init__.py
nlp_utils/embedding/chinese_characters.py
nlp_utils/embedding/export_numpy_to_checkpoint.py
nlp_utils/embedding/word_embedding.py
nlp_utils/preprocess/__init__.py
nlp_utils/preprocess/lookup_table.py
nlp_utils/preprocess/padding.py
nlp_utils/preprocess/read_embedding.py
nlp_utils/preprocess/seq.py
nlp_utils/preprocess/text_preprocess.py
nlp_utils/preprocess/clean/__init__.py
nlp_utils/preprocess/clean/char_delete.py
nlp_utils/preprocess/clean/chars_replace.py
nlp_utils/preprocess/clean/pattern_replace.py
nlp_utils/resources/fullwidth_to_halfwidth.json
nlp_utils/resources/gb2312_dict.json
nlp_utils/resources/number_to_normal.json
nlp_utils/resources/words.txt
nlp_utils/resources/zht_to_zhs.json
nlp_utils/text/__init__.py
nlp_utils/text/load_text.py
nlp_utils-0.6.2.dist-info/METADATA
nlp_utils-0.6.2.dist-info/WHEEL
nlp_utils-0.6.2.dist-info/top_level.txt
nlp_utils-0.6.2.dist-info/RECORD
