Metadata-Version: 2.1
Name: nlp-utils
Version: 0.6.2
Summary: Utils for NLP
Home-page: UNKNOWN
Author: Xiaoquan Kong
Author-email: u1mail2me@gmail.com
License: MIT
Platform: UNKNOWN
Provides-Extra: tensorflow
